{
	"$schema": "https://schemas.wp.org/trunk/block.json",
	"apiVersion": 3,
	"name": "acme-jobs/statuscache",
	"title": "Statuscache",
	"description": "Statuscache block generated from project config",
	"category": "widgets",
	"icon": "database",
	"textdomain": "acme-jobs",
	"keywords": ["statusCache"],
	"supports": {
		"align": ["wide", "full"],
		"color": {
			"background": true,
			"text": true
		},
		"spacing": {
			"margin": true,
			"padding": true
		},
		"typography": {
			"fontSize": true,
			"lineHeight": true
		}
	},
	"editorScriptModule": "file:./index.tsx",
	"viewScriptModule": "file:./view.ts"
}
